{"modelId": "BigSalmon/SimplifyText", "sha": "f1dcd3f3a42cf9f8515c8177e341c506e24dd9d2", "lastModified": "2021-10-14T00:41:11.000Z", "tags": ["pytorch", "gpt2", "text-generation", "transformers"], "pipeline_tag": "text-generation", "siblings": [{"rfilename": ".gitattributes"}, {"rfilename": "README.md"}, {"rfilename": "config.json"}, {"rfilename": "merges.txt"}, {"rfilename": "pytorch_model.bin"}, {"rfilename": "special_tokens_map.json"}, {"rfilename": "tokenizer.json"}, {"rfilename": "tokenizer_config.json"}, {"rfilename": "vocab.json"}], "config": {"architectures": ["GPT2LMHeadModel"], "model_type": "gpt2", "task_specific_params": {"text-generation": {"do_sample": true, "max_length": 50}}}, "private": false, "downloads": 13, "library_name": "transformers", "likes": 0}