{"modelId": "sentence-transformers/distilbert-base-nli-mean-tokens", "sha": "a7d0fe1c8fb2681ea4ec2c1a70eb7d22b1507961", "lastModified": "2021-08-05T08:19:05.000Z", "tags": ["pytorch", "distilbert", "feature-extraction", "arxiv:1908.10084", "sentence-transformers", "license:apache-2.0", "sentence-similarity", "transformers", "infinity_compatible"], "pipeline_tag": "feature-extraction", "siblings": [{"rfilename": ".gitattributes"}, {"rfilename": "README.md"}, {"rfilename": "config.json"}, {"rfilename": "config_sentence_transformers.json"}, {"rfilename": "modules.json"}, {"rfilename": "pytorch_model.bin"}, {"rfilename": "sentence_bert_config.json"}, {"rfilename": "special_tokens_map.json"}, {"rfilename": "tokenizer.json"}, {"rfilename": "tokenizer_config.json"}, {"rfilename": "vocab.txt"}, {"rfilename": "1_Pooling/config.json"}], "config": {"architectures": ["DistilBertModel"], "model_type": "distilbert"}, "private": false, "downloads": 108773, "library_name": "sentence-transformers", "likes": 0}