{"modelId": "HungChau/distilbert-base-uncased-concept-extraction-wikipedia-v1.0-concept-extraction-kp20k-v1.0", "sha": "59c48bdb0c1739b12d3c71d0f85f7ea81888d8eb", "lastModified": "2021-11-03T04:13:16.000Z", "tags": ["pytorch", "distilbert", "token-classification", "transformers", "autonlp_compatible", "infinity_compatible"], "pipeline_tag": "token-classification", "siblings": [{"rfilename": ".gitattributes"}, {"rfilename": "config.json"}, {"rfilename": "pytorch_model.bin"}, {"rfilename": "special_tokens_map.json"}, {"rfilename": "tokenizer.json"}, {"rfilename": "tokenizer_config.json"}, {"rfilename": "vocab.txt"}], "config": {"architectures": ["DistilBertForTokenClassification"], "model_type": "distilbert"}, "private": false, "downloads": 2, "library_name": "transformers", "likes": 0}