{"modelId": "erica/krm_sa3", "sha": "07f444be7a1fa55710da00412b6513bc9de7587e", "lastModified": "2021-11-24T03:17:12.000Z", "tags": ["pytorch", "bert", "text-classification", "transformers", "infinity_compatible"], "pipeline_tag": "text-classification", "siblings": [{"rfilename": ".DS_Store"}, {"rfilename": ".gitattributes"}, {"rfilename": "config.json"}, {"rfilename": "pytorch_model.bin"}, {"rfilename": "special_tokens_map.json"}, {"rfilename": "tokenizer.json"}, {"rfilename": "tokenizer_config.json"}, {"rfilename": "vocab.txt"}], "config": {"architectures": ["BertForSequenceClassification"], "model_type": "bert"}, "private": false, "downloads": 3, "library_name": "transformers", "likes": 0}