{"modelId": "Davlan/naija-twitter-sentiment-afriberta-large", "sha": "c9ab27a71796c919f4926766e3aa32648d4f259a", "lastModified": "2022-01-29T14:49:45.000Z", "tags": ["pytorch", "xlm-roberta", "text-classification", "hau", "ibo", "pcm", "yor", "multilingual", "arxiv:2201.08277", "transformers"], "pipeline_tag": "text-classification", "siblings": [{"rfilename": ".gitattributes"}, {"rfilename": "README.md"}, {"rfilename": "config.json"}, {"rfilename": "pytorch_model.bin"}, {"rfilename": "sentencepiece.bpe.model"}, {"rfilename": "special_tokens_map.json"}, {"rfilename": "tokenizer.json"}, {"rfilename": "tokenizer_config.json"}, {"rfilename": "training_args.bin"}], "config": {"architectures": ["XLMRobertaForSequenceClassification"], "model_type": "xlm-roberta"}, "private": false, "downloads": 1, "library_name": "transformers", "likes": 0}