{"modelId": "flair/ner-multi-fast", "sha": "80ebda976ff428db36b39fe71ec8d06f44bbff24", "lastModified": "2021-03-02T22:14:04.000Z", "tags": ["pytorch", "en de nl es", "dataset:conll2003", "flair", "token-classification", "sequence-tagger-model"], "pipeline_tag": "token-classification", "siblings": [{"rfilename": ".gitattributes"}, {"rfilename": "README.md"}, {"rfilename": "loss.tsv"}, {"rfilename": "pytorch_model.bin"}, {"rfilename": "training.log"}], "config": null, "private": false, "downloads": 95, "library_name": "flair", "likes": 0}