{"modelId": "mymusise/CPM-Generate-distill", "sha": "1611f575f3db84c83fd120ca8fd826953b4afdbf", "lastModified": "2021-05-23T10:40:31.000Z", "tags": ["pytorch", "tf", "jax", "gpt2", "text-generation", "zh", "transformers"], "pipeline_tag": "text-generation", "siblings": [{"rfilename": ".gitattributes"}, {"rfilename": "README.md"}, {"rfilename": "config.json"}, {"rfilename": "flax_model.msgpack"}, {"rfilename": "pytorch_model.bin"}, {"rfilename": "spiece.model"}, {"rfilename": "tf_model.h5"}], "config": {"architectures": ["GPT2LMHeadModel"], "model_type": "gpt2", "task_specific_params": {"text-generation": {"do_sample": true, "max_length": 120}}}, "private": false, "downloads": 123, "library_name": "transformers", "likes": 4}