{"modelId": "AdapterHub/bert-base-uncased-pf-quail", "sha": "e92f1286e721f96d3050424c351f3752b60624b9", "lastModified": "2021-11-24T16:24:59.000Z", "tags": ["bert", "en", "dataset:quail", "arxiv:2104.08247", "adapter-transformers", "infinity_compatible"], "pipeline_tag": null, "siblings": [{"rfilename": ".gitattributes"}, {"rfilename": "README.md"}, {"rfilename": "adapter_config.json"}, {"rfilename": "head_config.json"}, {"rfilename": "pytorch_adapter.bin"}, {"rfilename": "pytorch_model_head.bin"}], "config": {"model_type": "bert", "adapter_transformers": {"model_name": "bert-base-uncased", "model_class": "BertModelWithHeads"}}, "private": false, "downloads": 125, "library_name": "adapter-transformers", "likes": 0}