{"modelId": "reichenbach/mutlimodal-entailment", "sha": "b5366c91421813449988efd937d1ff8196be01c2", "lastModified": "2022-02-12T04:23:45.000Z", "tags": ["keras"], "pipeline_tag": null, "siblings": [{"rfilename": ".gitattributes"}, {"rfilename": "keras_metadata.pb"}, {"rfilename": "saved_model.pb"}, {"rfilename": "assets/vocab.txt"}, {"rfilename": "variables/variables.data-00000-of-00001"}, {"rfilename": "variables/variables.index"}], "config": null, "private": false, "downloads": 3, "library_name": "keras", "likes": 0}