{"modelId": "srush/bert_uncased_L-2_H-128_A-2", "sha": "56dc752de1d9f04222866dc6a4e61662a61e41bb", "lastModified": "2021-05-20T07:12:06.000Z", "tags": ["pytorch", "jax", "bert", "transformers", "infinity_compatible"], "pipeline_tag": null, "siblings": [{"rfilename": ".gitattributes"}, {"rfilename": "config.json"}, {"rfilename": "flax_model.msgpack"}, {"rfilename": "pytorch_model.bin"}, {"rfilename": "vocab.txt"}, {"rfilename": "model_cards/README.md"}], "config": {"model_type": "bert"}, "private": false, "downloads": 3, "library_name": "transformers", "likes": 0}