{"modelId": "GermanT5/german-t5-oscar-ep1-prompted-germanquad", "sha": "5176afcca863ecca7862a17eaee4415f1b6ab44d", "lastModified": "2022-01-25T09:03:14.000Z", "tags": ["pytorch", "tensorboard", "t5", "text2text-generation", "transformers", "generated_from_trainer", "model-index", "autonlp_compatible"], "pipeline_tag": "text2text-generation", "siblings": [{"rfilename": ".gitattributes"}, {"rfilename": "README.md"}, {"rfilename": "config.json"}, {"rfilename": "eval_results.txt"}, {"rfilename": "pytorch_model.bin"}, {"rfilename": "special_tokens_map.json"}, {"rfilename": "tokenizer.json"}, {"rfilename": "tokenizer_config.json"}, {"rfilename": "training_args.bin"}, {"rfilename": "runs/Jan24_15-40-29_ip-172-31-12-71/events.out.tfevents.1643038833.ip-172-31-12-71.74475.0"}, {"rfilename": "runs/Jan24_15-40-29_ip-172-31-12-71/events.out.tfevents.1643083668.ip-172-31-12-71.74475.2"}, {"rfilename": "runs/Jan24_15-40-29_ip-172-31-12-71/1643038833.5809927/events.out.tfevents.1643038833.ip-172-31-12-71.74475.1"}, {"rfilename": "runs/Jan25_07-19-46_ip-172-31-12-71/events.out.tfevents.1643095776.ip-172-31-12-71.290144.0"}, {"rfilename": "runs/Jan25_07-33-05_ip-172-31-12-71/events.out.tfevents.1643096566.ip-172-31-12-71.292319.0"}, {"rfilename": "runs/Jan25_07-44-00_ip-172-31-12-71/events.out.tfevents.1643101146.ip-172-31-12-71.294344.0"}], "config": {"architectures": ["T5ForConditionalGeneration"], "model_type": "t5"}, "private": false, "downloads": 5, "library_name": "transformers", "likes": 0}