{"modelId": "IDEA-CCNL/Zhouwenwang-110M", "sha": "8e1a5c50bc212dd5f377bfb016fd981764c3f415", "lastModified": "2021-11-26T04:16:38.000Z", "tags": ["pytorch", "megatron-bert", "zh", "transformers", "license:apache-2.0"], "pipeline_tag": null, "siblings": [{"rfilename": ".gitattributes"}, {"rfilename": "README.md"}, {"rfilename": "config.json"}, {"rfilename": "pytorch_model.bin"}, {"rfilename": "vocab.txt"}], "config": {"model_type": "megatron-bert"}, "private": false, "downloads": 84, "library_name": "transformers", "likes": 2}