{"modelId": "trueto/medbert-kd-chinese", "sha": "8a9aee70779f4069f8e7396d15a9f00ee1266843", "lastModified": "2021-05-20T08:10:57.000Z", "tags": ["pytorch", "jax", "bert", "pretraining", "transformers", "infinity_compatible"], "pipeline_tag": null, "siblings": [{"rfilename": ".gitattributes"}, {"rfilename": "README.md"}, {"rfilename": "config.json"}, {"rfilename": "flax_model.msgpack"}, {"rfilename": "pytorch_model.bin"}, {"rfilename": "vocab.txt"}], "config": {"architectures": ["BertForPreTraining"], "model_type": "bert"}, "private": false, "downloads": 468, "library_name": "transformers", "likes": 0}