{"modelId": "nbroad/mt5-base-qgen", "sha": "71c6fde4cb4c4f015fda94132674e5a465ca2af2", "lastModified": "2021-11-17T20:13:29.000Z", "tags": ["jax", "tensorboard", "mt5", "text2text-generation", "transformers", "autonlp_compatible"], "pipeline_tag": "text2text-generation", "siblings": [{"rfilename": ".gitattributes"}, {"rfilename": "README.md"}, {"rfilename": "config.json"}, {"rfilename": "events.out.tfevents.1635033358.t1v-n-ee54e442-w-0.39861.0.v2"}, {"rfilename": "flax_model.msgpack"}, {"rfilename": "run_summarization_flax.py"}, {"rfilename": "special_tokens_map.json"}, {"rfilename": "spiece.model"}, {"rfilename": "start_qgen.sh"}, {"rfilename": "tokenizer.json"}, {"rfilename": "tokenizer_config.json"}], "config": {"architectures": ["MT5ForConditionalGeneration"], "model_type": "mt5"}, "private": false, "downloads": 1, "library_name": "transformers", "likes": 0}