{"modelId": "AnjanBiswas/distilbert-base-uncased-finetuned-emotion", "sha": "33e597c5cb4a1c2046b7741056a9497105685e92", "lastModified": "2022-01-31T23:42:22.000Z", "tags": ["pytorch", "distilbert", "text-classification", "transformers", "infinity_compatible"], "pipeline_tag": "text-classification", "siblings": [{"rfilename": ".gitattributes"}, {"rfilename": ".gitignore"}, {"rfilename": "config.json"}, {"rfilename": "pytorch_model.bin"}, {"rfilename": "special_tokens_map.json"}, {"rfilename": "tokenizer.json"}, {"rfilename": "tokenizer_config.json"}, {"rfilename": "training_args.bin"}, {"rfilename": "vocab.txt"}], "config": {"architectures": ["DistilBertForSequenceClassification"], "model_type": "distilbert"}, "private": false, "downloads": 2, "library_name": "transformers", "likes": 0}