{"modelId": "dpasch01/finetune-data-skills", "sha": "011970e37c23f788afaf4b494bb5fbfcca7640ec", "lastModified": "2022-01-25T19:14:13.000Z", "tags": ["pytorch", "tensorboard", "bert", "fill-mask", "transformers", "license:apache-2.0", "generated_from_trainer", "model-index", "autonlp_compatible", "infinity_compatible"], "pipeline_tag": "fill-mask", "siblings": [{"rfilename": ".gitattributes"}, {"rfilename": ".gitignore"}, {"rfilename": "README.md"}, {"rfilename": "config.json"}, {"rfilename": "pytorch_model.bin"}, {"rfilename": "training_args.bin"}, {"rfilename": "runs/Jan25_17-16-22_d1f1fe4ae4f7/events.out.tfevents.1643130999.d1f1fe4ae4f7.76.0"}, {"rfilename": "runs/Jan25_17-16-22_d1f1fe4ae4f7/events.out.tfevents.1643137607.d1f1fe4ae4f7.76.2"}, {"rfilename": "runs/Jan25_17-16-22_d1f1fe4ae4f7/1643130999.2385/events.out.tfevents.1643130999.d1f1fe4ae4f7.76.1"}], "config": {"architectures": ["BertForMaskedLM"], "model_type": "bert"}, "private": false, "downloads": 20, "library_name": "transformers", "likes": 0}