{"modelId": "avichr/hebEMO_sadness", "sha": "e77841c6c509d53edf3cdae3086acaba643f820b", "lastModified": "2022-01-11T16:28:56.000Z", "tags": ["pytorch", "bert", "text-classification", "transformers", "infinity_compatible"], "pipeline_tag": "text-classification", "siblings": [{"rfilename": ".gitattributes"}, {"rfilename": "README.md"}, {"rfilename": "config.json"}, {"rfilename": "log_history.json"}, {"rfilename": "pytorch_model.bin"}, {"rfilename": "training_args.bin"}], "config": {"architectures": ["BertForSequenceClassification"], "model_type": "bert"}, "private": false, "downloads": 171, "library_name": "transformers", "likes": 0}