{"modelId": "google/realm-orqa-wq-openqa", "sha": "2f280ce6d6b92847268c1323100be02a24b859da", "lastModified": "2022-01-05T17:02:11.000Z", "tags": ["pytorch", "realm", "en", "transformers", "license:apache-2.0"], "pipeline_tag": null, "siblings": [{"rfilename": ".gitattributes"}, {"rfilename": "README.md"}, {"rfilename": "config.json"}, {"rfilename": "pytorch_model.bin"}, {"rfilename": "special_tokens_map.json"}, {"rfilename": "tokenizer_config.json"}, {"rfilename": "vocab.txt"}], "config": {"architectures": ["RealmForOpenQA"], "model_type": "realm"}, "private": false, "downloads": 4, "library_name": "transformers", "likes": 0}