{"modelId": "navteca/electra-base-squad2", "sha": "1983e4c58b41d0a967e957d5df8579f85543d861", "lastModified": "2021-08-10T14:30:25.000Z", "tags": ["pytorch", "electra", "question-answering", "en", "dataset:squad_v2", "transformers", "license:mit", "autonlp_compatible", "infinity_compatible"], "pipeline_tag": "question-answering", "siblings": [{"rfilename": ".gitattributes"}, {"rfilename": "README.md"}, {"rfilename": "config.json"}, {"rfilename": "pytorch_model.bin"}, {"rfilename": "special_tokens_map.json"}, {"rfilename": "tokenizer_config.json"}, {"rfilename": "vocab.txt"}], "config": {"architectures": ["ElectraForQuestionAnswering"], "model_type": "electra"}, "private": false, "downloads": 13, "library_name": "transformers", "likes": 0}