{"modelId": "gustavecortal/fr-boris-8bit", "sha": "65c4df25ccaa4ca96e389c24fdd1825bc507841b", "lastModified": "2022-01-11T13:09:16.000Z", "tags": ["pytorch", "gptj", "text-generation", "fr", "dataset:c4", "dataset:The Pile", "transformers", "license:mit", "causal-lm"], "pipeline_tag": "text-generation", "siblings": [{"rfilename": ".gitattributes"}, {"rfilename": "README.md"}, {"rfilename": "config.json"}, {"rfilename": "pytorch_model.bin"}], "config": {"architectures": ["GPTJForCausalLM"], "model_type": "gptj", "task_specific_params": {"text-generation": {"do_sample": true, "max_length": 50, "temperature": 1}}}, "private": false, "downloads": 336, "library_name": "transformers", "likes": 3}