{"modelId": "dbsamu/deberta-base-finetuned-ner", "sha": "78d2a24e72ddf68e980726259541f0609409b7f0", "lastModified": "2022-01-21T18:25:55.000Z", "tags": ["pytorch", "tensorboard", "deberta", "token-classification", "transformers", "autonlp_compatible"], "pipeline_tag": "token-classification", "siblings": [{"rfilename": ".gitattributes"}, {"rfilename": ".gitignore"}, {"rfilename": "config.json"}, {"rfilename": "merges.txt"}, {"rfilename": "pytorch_model.bin"}, {"rfilename": "special_tokens_map.json"}, {"rfilename": "tokenizer.json"}, {"rfilename": "tokenizer_config.json"}, {"rfilename": "training_args.bin"}, {"rfilename": "vocab.json"}, {"rfilename": "runs/Jan21_18-23-50_61dbe21cefcf/events.out.tfevents.1642789437.61dbe21cefcf.73.6"}, {"rfilename": "runs/Jan21_18-23-50_61dbe21cefcf/1642789437.19856/events.out.tfevents.1642789437.61dbe21cefcf.73.7"}], "config": {"architectures": ["DebertaForTokenClassification"], "model_type": "deberta"}, "private": false, "downloads": 8, "library_name": "transformers", "likes": 0}