{"modelId": "mrm8488/longformer-base-4096-spanish", "sha": "5af7ed401a5a0025632f9e4115d82da321b1fbc1", "lastModified": "2022-01-11T20:40:22.000Z", "tags": ["pytorch", "tensorboard", "roberta", "fill-mask", "es", "dataset:spanish_large_corpus", "arxiv:2004.05150", "transformers", "license:mit", "Long documents", "longformer", "bertin", "spanish", "autonlp_compatible", "infinity_compatible"], "pipeline_tag": "fill-mask", "siblings": [{"rfilename": ".gitattributes"}, {"rfilename": "README.md"}, {"rfilename": "config.json"}, {"rfilename": "merges.txt"}, {"rfilename": "pytorch_model.bin"}, {"rfilename": "special_tokens_map.json"}, {"rfilename": "tokenizer.json"}, {"rfilename": "tokenizer_config.json"}, {"rfilename": "vocab.json"}, {"rfilename": "runs/Jan03_20-28-55_a6b229e4fd6f/events.out.tfevents.1641241860.a6b229e4fd6f.127.0"}, {"rfilename": "runs/Jan03_20-28-55_a6b229e4fd6f/1641241860.181772/events.out.tfevents.1641241860.a6b229e4fd6f.127.1"}, {"rfilename": "runs/Jan03_21-01-39_a6b229e4fd6f/events.out.tfevents.1641243701.a6b229e4fd6f.127.2"}, {"rfilename": "runs/Jan03_21-01-39_a6b229e4fd6f/1641243701.7058358/events.out.tfevents.1641243701.a6b229e4fd6f.127.3"}], "config": {"architectures": ["RobertaLongForMaskedLM"], "model_type": "roberta"}, "private": false, "downloads": 140, "library_name": "transformers", "likes": 5}