{"modelId": "fav-kky/FERNET-CC_sk", "sha": "1a1d87d4ab1f64643de472334e690777d9de9cbc", "lastModified": "2021-09-09T13:42:54.000Z", "tags": ["pytorch", "tf", "bert", "fill-mask", "sk", "arxiv:2107.10042", "transformers", "Slovak", "KKY", "FAV", "license:cc-by-nc-sa-4.0", "autonlp_compatible", "infinity_compatible"], "pipeline_tag": "fill-mask", "siblings": [{"rfilename": ".gitattributes"}, {"rfilename": "README.md"}, {"rfilename": "config.json"}, {"rfilename": "pytorch_model.bin"}, {"rfilename": "special_tokens_map.json"}, {"rfilename": "tf_model.h5"}, {"rfilename": "tokenizer_config.json"}, {"rfilename": "vocab.txt"}], "config": {"architectures": ["BertForMaskedLM"], "model_type": "bert"}, "private": false, "downloads": 13, "library_name": "transformers", "likes": 0}