{"modelId": "GKLMIP/bert-laos-base-uncased", "sha": "cd5c26f0e2221a2326bda48d8781595723d6f443", "lastModified": "2021-07-31T06:12:22.000Z", "tags": ["pytorch", "bert", "fill-mask", "transformers", "autonlp_compatible", "infinity_compatible"], "pipeline_tag": "fill-mask", "siblings": [{"rfilename": ".gitattributes"}, {"rfilename": "README.md"}, {"rfilename": "config.json"}, {"rfilename": "lo.wiki.bpe.vs25000.model"}, {"rfilename": "pytorch_model.bin"}, {"rfilename": "tokenizer_config.json"}, {"rfilename": "vocab.txt"}], "config": {"architectures": ["BertForMaskedLM"], "model_type": "bert"}, "private": false, "downloads": 11, "library_name": "transformers", "likes": 0}