{"modelId": "microsoft/unispeech-sat-large-sd", "sha": "1e451cf8fdaa17c25d2a08d70511a06b22488e40", "lastModified": "2021-12-17T18:42:36.000Z", "tags": ["pytorch", "unispeech-sat", "audio-frame-classification", "en", "arxiv:1912.07875", "arxiv:2106.06909", "arxiv:2101.00390", "arxiv:2110.05752", "transformers", "speech"], "pipeline_tag": null, "siblings": [{"rfilename": ".gitattributes"}, {"rfilename": "README.md"}, {"rfilename": "config.json"}, {"rfilename": "preprocessor_config.json"}, {"rfilename": "pytorch_model.bin"}], "config": {"architectures": ["UniSpeechSatForAudioFrameClassification"], "model_type": "unispeech-sat"}, "private": false, "downloads": 100, "library_name": "transformers", "likes": 0}