{"modelId": "allenyummy/chinese-bert-wwm-ehr-ner-sl", "sha": "0020467f0a55b08401f9d94d3f5d7edc2d92c7e1", "lastModified": "2021-05-19T11:42:42.000Z", "tags": ["pytorch", "bert", "zh-tw", "transformers", "infinity_compatible"], "pipeline_tag": null, "siblings": [{"rfilename": ".gitattributes"}, {"rfilename": "README.md"}, {"rfilename": "added_tokens.json"}, {"rfilename": "config.json"}, {"rfilename": "pytorch_model.bin"}, {"rfilename": "special_tokens_map.json"}, {"rfilename": "tokenizer_config.json"}, {"rfilename": "training_args.bin"}, {"rfilename": "vocab.txt"}], "config": {"architectures": ["CustomBertNER"], "model_type": "bert"}, "private": false, "downloads": 10, "library_name": "transformers", "likes": 0}