{"modelId": "stanfordnlp/stanza-cs", "sha": "68da4292dc8973122a089ae26eef02e3bf341325", "lastModified": "2021-12-16T08:03:44.000Z", "tags": ["cs", "stanza", "token-classification", "license:apache-2.0"], "pipeline_tag": "token-classification", "siblings": [{"rfilename": ".gitattributes"}, {"rfilename": "README.md"}, {"rfilename": "models/default.zip"}, {"rfilename": "models/depparse/cac.pt"}, {"rfilename": "models/depparse/cltt.pt"}, {"rfilename": "models/depparse/fictree.pt"}, {"rfilename": "models/depparse/pdt.pt"}, {"rfilename": "models/lemma/cac.pt"}, {"rfilename": "models/lemma/cltt.pt"}, {"rfilename": "models/lemma/fictree.pt"}, {"rfilename": "models/lemma/pdt.pt"}, {"rfilename": "models/mwt/cac.pt"}, {"rfilename": "models/mwt/cltt.pt"}, {"rfilename": "models/mwt/fictree.pt"}, {"rfilename": "models/mwt/pdt.pt"}, {"rfilename": "models/pos/cac.pt"}, {"rfilename": "models/pos/cltt.pt"}, {"rfilename": "models/pos/fictree.pt"}, {"rfilename": "models/pos/pdt.pt"}, {"rfilename": "models/pretrain/cac.pt"}, {"rfilename": "models/pretrain/cltt.pt"}, {"rfilename": "models/pretrain/fictree.pt"}, {"rfilename": "models/pretrain/pdt.pt"}, {"rfilename": "models/tokenize/cac.pt"}, {"rfilename": "models/tokenize/cltt.pt"}, {"rfilename": "models/tokenize/fictree.pt"}, {"rfilename": "models/tokenize/pdt.pt"}], "config": null, "private": false, "downloads": 18, "library_name": "stanza", "likes": 0}