{"modelId": "briancporter/winogrande-roberta", "sha": "8bdff136501bc12216424e8af20e3efe768dbe18", "lastModified": "2021-11-06T06:26:38.000Z", "tags": ["tf", "roberta", "text-classification", "transformers", "infinity_compatible"], "pipeline_tag": "text-classification", "siblings": [{"rfilename": ".gitattributes"}, {"rfilename": "config.json"}, {"rfilename": "tf_model.h5"}], "config": {"architectures": ["RobertaForSequenceClassification"], "model_type": "roberta"}, "private": false, "downloads": 13, "library_name": "transformers", "likes": 0}