{"modelId": "nateraw/hot-dog", "sha": "dc768435246614205e59fcd0412937c6bb116083", "lastModified": "2021-07-01T05:31:18.000Z", "tags": ["pytorch", "detr", "object-detection", "transformers"], "pipeline_tag": "object-detection", "siblings": [{"rfilename": ".gitattributes"}, {"rfilename": "README.md"}, {"rfilename": "config.json"}, {"rfilename": "preprocessor_config.json"}, {"rfilename": "pytorch_model.bin"}], "config": {"architectures": ["DetrForObjectDetection"], "model_type": "detr"}, "private": false, "downloads": 74, "library_name": "transformers", "likes": 0}