{"modelId": "ysharma/dummy-model-2", "sha": "6fa13bfd2b75228aca61f1889896ef297e9b6bb3", "lastModified": "2021-07-12T06:25:53.000Z", "tags": ["pytorch", "camembert", "fill-mask", "transformers", "autonlp_compatible"], "pipeline_tag": "fill-mask", "siblings": [{"rfilename": ".gitattributes"}, {"rfilename": "config.json"}, {"rfilename": "pytorch_model.bin"}, {"rfilename": "sentencepiece.bpe.model"}, {"rfilename": "special_tokens_map.json"}, {"rfilename": "tokenizer.json"}, {"rfilename": "tokenizer_config.json"}], "config": {"architectures": ["CamembertForMaskedLM"], "model_type": "camembert"}, "private": false, "downloads": 4, "library_name": "transformers", "likes": 0}