{"modelId": "ami-wav2vec2/wav2vec2-base-ami_multi-nithin3", "sha": "e1135bad5257e58dd236e4938ab0020152a55a44", "lastModified": "2021-10-22T08:56:04.000Z", "tags": ["pytorch", "tensorboard", "wav2vec2", "automatic-speech-recognition", "en", "transformers", "license:apache-2.0", "ami", "generated_from_trainer", "model-index"], "pipeline_tag": "automatic-speech-recognition", "siblings": [{"rfilename": ".gitattributes"}, {"rfilename": ".gitignore"}, {"rfilename": "README.md"}, {"rfilename": "all_results.json"}, {"rfilename": "config.json"}, {"rfilename": "eval.py"}, {"rfilename": "eval_results.json"}, {"rfilename": "preprocessor_config.json"}, {"rfilename": "pytorch_model.bin"}, {"rfilename": "run_main.sh"}, {"rfilename": "run_speech_recognition_ctc.py"}, {"rfilename": "special_tokens_map.json"}, {"rfilename": "tokenizer_config.json"}, {"rfilename": "train_results.json"}, {"rfilename": "trainer_state.json"}, {"rfilename": "training_args.bin"}, {"rfilename": "vocab.json"}, {"rfilename": "runs/Oct17_05-38-36_gpu-2-v100-experiments/events.out.tfevents.1634451268.gpu-2-v100-experiments.139180.0"}, {"rfilename": "runs/Oct17_05-38-36_gpu-2-v100-experiments/events.out.tfevents.1634573891.gpu-2-v100-experiments.139180.2"}, {"rfilename": "runs/Oct17_05-38-36_gpu-2-v100-experiments/1634451268.4132285/events.out.tfevents.1634451268.gpu-2-v100-experiments.139180.1"}], "config": {"architectures": ["Wav2Vec2ForCTC"], "model_type": "wav2vec2"}, "private": false, "downloads": 3, "library_name": "transformers", "likes": 0}