{"modelId": "JorisCos/DPTNet_Libri1Mix_enhsingle_16k", "sha": "935f441c53e44d40ca0cf138f71e850defc8bea5", "lastModified": "2021-09-23T15:49:20.000Z", "tags": ["pytorch", "dataset:Libri1Mix", "dataset:enh_single", "asteroid", "audio", "DPTNet", "audio-to-audio", "license:cc-by-sa-4.0"], "pipeline_tag": "audio-to-audio", "siblings": [{"rfilename": ".gitattributes"}, {"rfilename": "README.md"}, {"rfilename": "pytorch_model.bin"}], "config": null, "private": false, "downloads": 56, "library_name": "asteroid", "likes": 0}