{"modelId": "wandemberg-eld/opus-mt-en-de-finetuned-en-to-de-model-2", "sha": "ff7fe7b5df43635ddbbea749e51ef1fd828f6468", "lastModified": "2021-12-03T05:02:08.000Z", "tags": ["pytorch", "marian", "text2text-generation", "dataset:wmt16", "transformers", "license:apache-2.0", "generated_from_trainer", "model-index", "autonlp_compatible"], "pipeline_tag": "text2text-generation", "siblings": [{"rfilename": ".gitattributes"}, {"rfilename": ".gitignore"}, {"rfilename": "README.md"}, {"rfilename": "config.json"}, {"rfilename": "pytorch_model.bin"}, {"rfilename": "source.spm"}, {"rfilename": "special_tokens_map.json"}, {"rfilename": "target.spm"}, {"rfilename": "tokenizer_config.json"}, {"rfilename": "training_args.bin"}, {"rfilename": "vocab.json"}], "config": {"architectures": ["MarianMTModel"], "model_type": "marian"}, "private": false, "downloads": 1, "library_name": "transformers", "likes": 0}