{"modelId": "nateraw/planes-trains-automobiles", "sha": "dcf495d94e1cb0e9e7fb6bf8ac3c05c74dc3c8df", "lastModified": "2021-08-23T21:42:21.000Z", "tags": ["pytorch", "tensorboard", "vit", "image-classification", "transformers", "license:apache-2.0", "huggingpics", "generated_from_trainer"], "pipeline_tag": "image-classification", "siblings": [{"rfilename": ".gitattributes"}, {"rfilename": ".gitignore"}, {"rfilename": "README.md"}, {"rfilename": "all_results.json"}, {"rfilename": "config.json"}, {"rfilename": "preprocessor_config.json"}, {"rfilename": "pytorch_model.bin"}, {"rfilename": "train_results.json"}, {"rfilename": "trainer_state.json"}, {"rfilename": "training_args.bin"}, {"rfilename": "images/automobiles.jpg"}, {"rfilename": "images/planes.jpg"}, {"rfilename": "images/trains.jpg"}, {"rfilename": "runs/Aug23_21-37-56_90489a400d03/events.out.tfevents.1629754680.90489a400d03.658.12"}, {"rfilename": "runs/Aug23_21-37-56_90489a400d03/1629754680.1882749/events.out.tfevents.1629754680.90489a400d03.658.13"}], "config": {"architectures": ["ViTForImageClassification"], "model_type": "vit"}, "private": false, "downloads": 1, "library_name": "transformers", "likes": 0}