{"modelId": "DeskDown/MarianMixFT_en-vi", "sha": "4ea0a16201d5cd31fb0783b3d43164188e3d9f71", "lastModified": "2022-01-14T22:59:35.000Z", "tags": ["pytorch", "marian", "text2text-generation", "transformers", "autonlp_compatible"], "pipeline_tag": "text2text-generation", "siblings": [{"rfilename": ".gitattributes"}, {"rfilename": "config.json"}, {"rfilename": "pytorch_model.bin"}], "config": {"architectures": ["MarianMTModel"], "model_type": "marian"}, "private": false, "downloads": 5, "library_name": "transformers", "likes": 0}