{"modelId": "facebook/detr-resnet-101", "sha": "5fb693ac13144810a03c3320028208de1dc75a5b", "lastModified": "2021-11-03T16:17:51.000Z", "tags": ["pytorch", "detr", "object-detection", "dataset:coco", "arxiv:2005.12872", "transformers", "license:apache-2.0"], "pipeline_tag": "object-detection", "siblings": [{"rfilename": ".gitattributes"}, {"rfilename": "README.md"}, {"rfilename": "config.json"}, {"rfilename": "preprocessor_config.json"}, {"rfilename": "pytorch_model.bin"}], "config": {"architectures": ["DetrForObjectDetection"], "model_type": "detr"}, "private": false, "downloads": 275, "library_name": "transformers", "likes": 0}