{"modelId": "fnlp/elasticbert-large", "sha": "0a5689cea93ed0bf88c87bcd623e0de0f98516e2", "lastModified": "2021-10-28T11:05:49.000Z", "tags": ["pytorch", "elasticbert", "fill-mask", "arxiv:2110.07038", "transformers", "autonlp_compatible"], "pipeline_tag": "fill-mask", "siblings": [{"rfilename": ".gitattributes"}, {"rfilename": "README.md"}, {"rfilename": "config.json"}, {"rfilename": "pytorch_model.bin"}, {"rfilename": "tokenizer.json"}, {"rfilename": "tokenizer_config.json"}, {"rfilename": "vocab.txt"}], "config": {"architectures": ["ElasticBertForMaskedLM"], "model_type": "elasticbert"}, "private": false, "downloads": 3, "library_name": "transformers", "likes": 2}