{"modelId": "qqhann/w2v_hf_commonvoice_from_xlsr53_pretrain_0329UTC1500", "sha": "bfb4994e32547ea47719acf43eec5e1f7a46b41a", "lastModified": "2021-04-01T15:16:55.000Z", "tags": ["pytorch", "wav2vec2", "automatic-speech-recognition", "transformers"], "pipeline_tag": "automatic-speech-recognition", "siblings": [{"rfilename": ".gitattributes"}, {"rfilename": "README.md"}, {"rfilename": "config.json"}, {"rfilename": "preprocessor_config.json"}, {"rfilename": "pytorch_model.bin"}, {"rfilename": "special_tokens_map.json"}, {"rfilename": "tokenizer_config.json"}, {"rfilename": "vocab.json"}], "config": {"architectures": ["Wav2Vec2ForCTC"], "model_type": "wav2vec2"}, "private": false, "downloads": 2, "library_name": "transformers", "likes": 0}