{"modelId": "HungChau/distilbert-base-cased-concept-extraction-iir-v1.2-concept-extraction-kp20k-v1.5", "sha": "4cc3fd91cc082af2a05ab1e3eb985ed21efd6588", "lastModified": "2021-11-19T22:12:59.000Z", "tags": ["pytorch", "distilbert", "token-classification", "transformers", "autonlp_compatible", "infinity_compatible"], "pipeline_tag": "token-classification", "siblings": [{"rfilename": ".gitattributes"}, {"rfilename": "config.json"}, {"rfilename": "pytorch_model.bin"}, {"rfilename": "special_tokens_map.json"}, {"rfilename": "tokenizer.json"}, {"rfilename": "tokenizer_config.json"}, {"rfilename": "vocab.txt"}], "config": {"architectures": ["DistilBertForTokenClassification"], "model_type": "distilbert"}, "private": false, "downloads": 2, "library_name": "transformers", "likes": 0}