{"modelId": "bstad/a-different-bert-model", "sha": "d92111a3b75af9ea69905426a6080399234a6f30", "lastModified": "2021-12-28T01:58:01.000Z", "tags": ["pytorch", "bert", "fill-mask", "transformers", "autonlp_compatible", "infinity_compatible"], "pipeline_tag": "fill-mask", "siblings": [{"rfilename": ".gitattributes"}, {"rfilename": "config.json"}, {"rfilename": "pytorch_model.bin"}, {"rfilename": "special_tokens_map.json"}, {"rfilename": "tokenizer.json"}, {"rfilename": "tokenizer_config.json"}, {"rfilename": "vocab.txt"}], "config": {"architectures": ["BertForMaskedLM"], "model_type": "bert"}, "private": false, "downloads": 4, "library_name": "transformers", "likes": 0}