{"modelId": "yzhou992/NetMind-20211104-781", "sha": "978e11f554ed79c1a32c0e51493eed683a635c49", "lastModified": "2021-11-04T08:38:46.000Z", "tags": ["pytorch", "albert", "pretraining", "transformers", "infinity_compatible"], "pipeline_tag": null, "siblings": [{"rfilename": ".gitattributes"}, {"rfilename": "config.json"}, {"rfilename": "optimizer_state.pt"}, {"rfilename": "pytorch_model.bin"}], "config": {"architectures": ["AlbertForPreTraining"], "model_type": "albert"}, "private": false, "downloads": 2, "library_name": "transformers", "likes": 0}