{"modelId": "kevinzyz/chinese-bert-wwm-ext-finetuned-cola", "sha": "b296af42cd0973cdc07ef36293094595cecab646", "lastModified": "2021-11-19T03:13:39.000Z", "tags": ["pytorch", "tensorboard", "bert", "text-classification", "transformers", "license:apache-2.0", "generated_from_trainer", "model-index", "infinity_compatible"], "pipeline_tag": "text-classification", "siblings": [{"rfilename": ".gitattributes"}, {"rfilename": ".gitignore"}, {"rfilename": "README.md"}, {"rfilename": "config.json"}, {"rfilename": "pytorch_model.bin"}, {"rfilename": "special_tokens_map.json"}, {"rfilename": "tokenizer_config.json"}, {"rfilename": "training_args.bin"}, {"rfilename": "vocab.txt"}, {"rfilename": "runs/Nov18_12-49-11_cpdp151/events.out.tfevents.1637211017.cpdp151.22814.0"}, {"rfilename": "runs/Nov18_12-49-11_cpdp151/1637211017.1931508/events.out.tfevents.1637211017.cpdp151.22814.1"}, {"rfilename": "runs/Nov18_19-38-47_cpdp151/events.out.tfevents.1637235540.cpdp151.15697.0"}, {"rfilename": "runs/Nov18_19-38-47_cpdp151/1637235540.6463654/events.out.tfevents.1637235540.cpdp151.15697.1"}, {"rfilename": "runs/Nov18_21-47-12_cpdp151/events.out.tfevents.1637243232.cpdp151.22183.35.v2"}, {"rfilename": "runs/Nov18_22-00-21_cpdp151/events.out.tfevents.1637244035.cpdp151.25652.0"}, {"rfilename": "runs/Nov18_22-00-21_cpdp151/1637244035.0553043/events.out.tfevents.1637244035.cpdp151.25652.1"}], "config": {"architectures": ["BertForSequenceClassification"], "model_type": "bert"}, "private": false, "downloads": 25, "library_name": "transformers", "likes": 0}