{"modelId": "HooshvareLab/roberta-fa-zwnj-base", "sha": "62eabb60447b49d9df5dabec5f44df6966f8108c", "lastModified": "2021-05-20T11:56:49.000Z", "tags": ["pytorch", "tf", "jax", "roberta", "fill-mask", "fa", "transformers", "license:apache-2.0", "autonlp_compatible", "infinity_compatible"], "pipeline_tag": "fill-mask", "siblings": [{"rfilename": ".gitattributes"}, {"rfilename": "README.md"}, {"rfilename": "config.json"}, {"rfilename": "flax_model.msgpack"}, {"rfilename": "merges.txt"}, {"rfilename": "pytorch_model.bin"}, {"rfilename": "special_tokens_map.json"}, {"rfilename": "tf_model.h5"}, {"rfilename": "tokenizer.json"}, {"rfilename": "tokenizer_config.json"}, {"rfilename": "vocab.json"}], "config": {"architectures": ["RobertaForMaskedLM"], "model_type": "roberta"}, "private": false, "downloads": 300, "library_name": "transformers", "likes": 0}