{"modelId": "yamako/dummy-model", "sha": "5544bb242919cd4ddf14bc4f66003b644d25e54b", "lastModified": "2021-09-07T11:32:36.000Z", "tags": ["pytorch", "camembert", "fill-mask", "transformers", "autonlp_compatible"], "pipeline_tag": "fill-mask", "siblings": [{"rfilename": ".gitattributes"}, {"rfilename": "config.json"}, {"rfilename": "pytorch_model.bin"}], "config": {"architectures": ["CamembertForMaskedLM"], "model_type": "camembert"}, "private": false, "downloads": 3, "library_name": "transformers", "likes": 0}