{"modelId": "mattchurgin/bert-finetuned-ner", "sha": "39d485afdf7c51299e577338c2b5be3c43dd3652", "lastModified": "2022-01-20T22:16:43.000Z", "tags": ["pytorch", "bert", "token-classification", "transformers", "autonlp_compatible", "infinity_compatible"], "pipeline_tag": "token-classification", "siblings": [{"rfilename": ".gitattributes"}, {"rfilename": ".gitignore"}, {"rfilename": "config.json"}, {"rfilename": "pytorch_model.bin"}, {"rfilename": "special_tokens_map.json"}, {"rfilename": "tokenizer.json"}, {"rfilename": "tokenizer_config.json"}, {"rfilename": "training_args.bin"}, {"rfilename": "vocab.txt"}], "config": {"architectures": ["BertForTokenClassification"], "model_type": "bert"}, "private": false, "downloads": 5, "library_name": "transformers", "likes": 0}