{"modelId": "ehcalabres/wav2vec2-lg-xlsr-en-speech-emotion-recognition", "sha": "17cf17c4ec7c4d083a3ac50a3c98d44088434cee", "lastModified": "2021-09-21T20:59:32.000Z", "tags": ["pytorch", "tensorboard", "wav2vec2", "audio-classification", "transformers", "license:apache-2.0", "generated_from_trainer"], "pipeline_tag": "audio-classification", "siblings": [{"rfilename": ".gitattributes"}, {"rfilename": ".gitignore"}, {"rfilename": "README.md"}, {"rfilename": "config.json"}, {"rfilename": "preprocessor_config.json"}, {"rfilename": "pytorch_model.bin"}, {"rfilename": "training_args.bin"}, {"rfilename": "runs/Jul14_08-52-02_ea6be2bf8cd5/events.out.tfevents.1626253006.ea6be2bf8cd5.900.4"}, {"rfilename": "runs/Jul14_08-52-02_ea6be2bf8cd5/1626253006.9531522/events.out.tfevents.1626253006.ea6be2bf8cd5.900.5"}, {"rfilename": "runs/Jul14_08-58-15_ea6be2bf8cd5/events.out.tfevents.1626253103.ea6be2bf8cd5.1946.0"}, {"rfilename": "runs/Jul14_08-58-15_ea6be2bf8cd5/1626253103.0537474/events.out.tfevents.1626253103.ea6be2bf8cd5.1946.1"}, {"rfilename": "runs/Sep21_17-17-21_cc179d296121/events.out.tfevents.1632245116.cc179d296121.76.0"}, {"rfilename": "runs/Sep21_17-17-21_cc179d296121/1632245116.2700055/events.out.tfevents.1632245116.cc179d296121.76.1"}], "config": {"architectures": ["Wav2Vec2ForSequenceClassification"], "model_type": "wav2vec2"}, "private": false, "downloads": 1543, "library_name": "transformers", "likes": 8}