{"modelId": "indridinn/distilbert-base-uncased-finetuned-ner", "sha": "fbcc692e4a78f2e53edb1ff4af0c9d9ecba8b451", "lastModified": "2021-10-01T22:29:15.000Z", "tags": ["pytorch", "tensorboard", "distilbert", "token-classification", "dataset:conll2003", "transformers", "license:apache-2.0", "generated_from_trainer", "model-index", "autonlp_compatible", "infinity_compatible"], "pipeline_tag": "token-classification", "siblings": [{"rfilename": ".gitattributes"}, {"rfilename": ".gitignore"}, {"rfilename": "README.md"}, {"rfilename": "config.json"}, {"rfilename": "pytorch_model.bin"}, {"rfilename": "special_tokens_map.json"}, {"rfilename": "tokenizer.json"}, {"rfilename": "tokenizer_config.json"}, {"rfilename": "training_args.bin"}, {"rfilename": "vocab.txt"}, {"rfilename": "runs/Oct01_19-05-16_6f3213b36f5c/events.out.tfevents.1633116466.6f3213b36f5c.65.0"}, {"rfilename": "runs/Oct01_19-05-16_6f3213b36f5c/events.out.tfevents.1633126927.6f3213b36f5c.65.2"}, {"rfilename": "runs/Oct01_19-05-16_6f3213b36f5c/1633116466.8987868/events.out.tfevents.1633116466.6f3213b36f5c.65.1"}], "config": {"architectures": ["DistilBertForTokenClassification"], "model_type": "distilbert"}, "private": false, "downloads": 4, "library_name": "transformers", "likes": 0}