{"modelId": "s3h/arabert-gec-v2-2", "sha": "1e62b3b02164961c96decbe585d60982b73db3d0", "lastModified": "2022-01-01T18:50:19.000Z", "tags": ["t5", "text2text-generation", "transformers", "generated_from_keras_callback", "model-index", "autonlp_compatible"], "pipeline_tag": "text2text-generation", "siblings": [{"rfilename": ".gitattributes"}, {"rfilename": "README.md"}, {"rfilename": "config.json"}, {"rfilename": "special_tokens_map.json"}, {"rfilename": "tokenizer.json"}, {"rfilename": "tokenizer_config.json"}], "config": {"architectures": ["T5ForConditionalGeneration"], "model_type": "t5"}, "private": false, "downloads": 4, "library_name": "transformers", "likes": 0}