{"modelId": "RenZHU/t5-small-finetuned-xsum", "sha": "2b027b118bf561e44f7153a0be147dcec0ea225d", "lastModified": "2022-01-09T03:09:55.000Z", "tags": ["pytorch", "tensorboard", "t5", "text2text-generation", "transformers", "license:apache-2.0", "generated_from_trainer", "model-index", "autonlp_compatible"], "pipeline_tag": "text2text-generation", "siblings": [{"rfilename": ".gitattributes"}, {"rfilename": ".gitignore"}, {"rfilename": "README.md"}, {"rfilename": "config.json"}, {"rfilename": "pytorch_model.bin"}, {"rfilename": "special_tokens_map.json"}, {"rfilename": "spiece.model"}, {"rfilename": "tokenizer.json"}, {"rfilename": "tokenizer_config.json"}, {"rfilename": "training_args.bin"}, {"rfilename": "runs/Dec08_09-36-05_4944c2143cb1/events.out.tfevents.1638956179.4944c2143cb1.85.0"}, {"rfilename": "runs/Dec08_09-36-05_4944c2143cb1/1638956179.2921455/events.out.tfevents.1638956179.4944c2143cb1.85.1"}, {"rfilename": "runs/Dec08_10-31-24_4944c2143cb1/events.out.tfevents.1638959493.4944c2143cb1.85.2"}, {"rfilename": "runs/Dec08_10-31-24_4944c2143cb1/1638959493.9480443/events.out.tfevents.1638959493.4944c2143cb1.85.3"}, {"rfilename": "runs/Dec08_10-31-24_4944c2143cb1/1638959596.3120546/events.out.tfevents.1638959596.4944c2143cb1.85.4"}, {"rfilename": "runs/Dec15_11-37-34_7bf09c10f7a6/events.out.tfevents.1639568282.7bf09c10f7a6.108.0"}, {"rfilename": "runs/Dec15_11-37-34_7bf09c10f7a6/1639568282.1666393/events.out.tfevents.1639568282.7bf09c10f7a6.108.1"}, {"rfilename": "runs/Jan09_01-38-09_6cb1e3579a84/events.out.tfevents.1641692309.6cb1e3579a84.105.0"}, {"rfilename": "runs/Jan09_01-38-09_6cb1e3579a84/1641692309.351278/events.out.tfevents.1641692309.6cb1e3579a84.105.1"}, {"rfilename": "runs/Nov10_08-42-55_cbd728be2fdf/events.out.tfevents.1636533792.cbd728be2fdf.89.0"}, {"rfilename": "runs/Nov10_08-42-55_cbd728be2fdf/1636533793.0031579/events.out.tfevents.1636533793.cbd728be2fdf.89.1"}], "config": {"architectures": ["T5ForConditionalGeneration"], "model_type": "t5", "task_specific_params": {"summarization": {"early_stopping": true, "length_penalty": 2, "max_length": 200, "min_length": 30, "no_repeat_ngram_size": 3, "num_beams": 4, "prefix": "summarize: "}, "translation_en_to_de": {"early_stopping": true, "max_length": 300, "num_beams": 4, "prefix": "translate English to German: "}, "translation_en_to_fr": {"early_stopping": true, "max_length": 300, "num_beams": 4, "prefix": "translate English to French: "}, "translation_en_to_ro": {"early_stopping": true, "max_length": 300, "num_beams": 4, "prefix": "translate English to Romanian: "}}}, "private": false, "downloads": 178, "library_name": "transformers", "likes": 1}